setup.py
marigoso/__init__.py
marigoso/abstract.py
marigoso/browser.py
marigoso/interface.py
marigoso/notebook_import.py
marigoso/test.py
marigoso.egg-info/PKG-INFO
marigoso.egg-info/SOURCES.txt
marigoso.egg-info/dependency_links.txt
marigoso.egg-info/requires.txt
marigoso.egg-info/top_level.txt