Metadata-Version: 1.1
Name: marigoso
Version: 0.2.25
Summary: Functional Testing Tools for end to end testing of web applications and APIs.
Home-page: https://github.com/ldiary/marigoso
Author: Ernesto D. Luzon Jr.
Author-email: please_raise_a_bug_in_myrepo@github.com
License: MIT license
Platform: UNKNOWN
Classifier: Development Status :: 3 - Alpha
Classifier: Intended Audience :: Developers
Classifier: License :: OSI Approved :: MIT License
Classifier: Operating System :: POSIX
Classifier: Operating System :: Microsoft :: Windows
Classifier: Operating System :: MacOS :: MacOS X
Classifier: Topic :: Software Development :: Testing
Classifier: Topic :: Software Development :: Quality Assurance
Classifier: Programming Language :: Python
Classifier: Topic :: Software Development :: Libraries
Classifier: Topic :: Utilities
Classifier: Programming Language :: Python :: 3
